quickdl/__init__.py
quickdl-0.0.2.dist-info/LICENSE
quickdl-0.0.2.dist-info/METADATA
quickdl-0.0.2.dist-info/WHEEL
quickdl-0.0.2.dist-info/top_level.txt
quickdl-0.0.2.dist-info/RECORD
