Metadata-Version: 2.1
Name: quickdl
Version: 0.0.2
Summary: A simple file downloader
Home-page: https://github.com/manbehindthemadness/quickdl
Author: Manbehindthemadness
Author-email: manbehindthemadness@gmail.com
Classifier: Programming Language :: Python :: 3
Classifier: License :: OSI Approved :: MIT License
Classifier: Operating System :: OS Independent
Requires-Python: >=3.10
License-File: LICENSE
